setup.py
telegramapy/__init__.py
telegramapy/api.py
telegramapy/exception.py
telegramapy.egg-info/PKG-INFO
telegramapy.egg-info/SOURCES.txt
telegramapy.egg-info/dependency_links.txt
telegramapy.egg-info/not-zip-safe
telegramapy.egg-info/requires.txt
telegramapy.egg-info/top_level.txt
telegramapy/types/__init__.py
telegramapy/types/audio.py
telegramapy/types/chat.py
telegramapy/types/chataction.py
telegramapy/types/contact.py
telegramapy/types/document.py
telegramapy/types/file.py
telegramapy/types/forcereply.py
telegramapy/types/location.py
telegramapy/types/message.py
telegramapy/types/photosize.py
telegramapy/types/replaykeyboardhide.py
telegramapy/types/replaykeyboardmarkup.py
telegramapy/types/sticker.py
telegramapy/types/update.py
telegramapy/types/user.py
telegramapy/types/userprofilephotos.py
telegramapy/types/video.py
telegramapy/types/voice.py