Metadata-Version: 1.0
Name: telegramapy
Version: 0.1.1
Summary: Library for interacting with the Telegram Bot API.
Home-page: https://github.com/aadeg/TelegramAPy
Author: Giove Andrea
Author-email: andreagiove@outlook.com
License: GNU GPL v2.0
Platform: UNKNOWN
